Aleatory_Sync_Counter_flip-Flop_D/design.sv
//Representar uma saídaaleatória 4-1-6-5-2-3-7-0
module counter_d_3x8_aleatory (
  input wire clk,
  input wire reset,
  output reg [2:0]led
);
  reg [2:0] Q;
  wire [2:0] D;
  
  // Lógica sequencial (flip-flop com reset assíncrono)
  always @(posedge clk or posedge reset) begin
	if (reset)
	  Q <= 3'b000;
	else
	  Q <= D;
  end
  
    // Lógica combinacional para o próximo estado (D) 
  assign D[2] = (~Q[2] & ~Q[1]) | (~Q[2] & Q[0] | Q[2] & Q[1] & ~Q[0]);
  assign D[1] = (~Q[1] & Q[0]) | (~Q[2] & Q[1]);
  assign D[0] = (~Q[2] & Q[1]) | (Q[2] & ~Q[0]);
  

  assign led = Q;

endmodule

Aleatory_Sync_Counter_flip-Flop_D/testbench.sv
module tb_counter_d_3x8_aleatory;
  reg clk;
  reg reset;
  wire [2:0] led;
  
  // Instancia o módulo a ser testado (UUT - Unit Under Test)
  counter_d_3x8_aleatory uut (
    .clk(clk),
    .reset(reset),
    .led(led)
  );

    initial clk = 1'b0;
    // Alterna a cada 5 unidades de tempo
    always #5 clk = ~clk;
  
    // Inicializando a gravação de dump para ondas
  initial begin
    $dumpfile("counter_d_3x8_aleatory.vcd"); 
    $dumpvars(0, tb_counter_d_3x8_aleatory);
  end

   
  initial begin
    reset = 1'b0;
    #15 reset = 1'b1;
    #10 reset = 1'b0;
  end  

  initial begin
    #200;
    $finish;
  end
  
  initial $monitor("t=%0t ns, reset=%b, led=%b", $time, reset, led);
  
endmodule

Aleatory_Sync_Counter_flip-Flop_D/counter_d_3x8_aleatory.vcd
$date
    Aug 24, 2025  13:54:34
$end
$version
    TOOL:	xmsim	23.09-s001
$end
$timescale
    1 ns
$end

$scope module tb_counter_d_3x8_aleatory $end
$var reg       1 !    clk $end
$var reg       1 "    reset $end
$var wire      3 #    led [2:0] $end

$scope module uut $end
$var wire      1 $    clk  $end
$var wire      1 %    reset  $end
$var reg       3 &    led [2:0] $end
$var reg       3 '    Q [2:0] $end
$var wire      3 (    D [2:0] $end
$upscope $end

$upscope $end

$enddefinitions $end
$dumpvars
0!
0"
bx #
0$
0%
bx &
bx '
bx (
$end
#5
1!
1$
#10
0!
0$
#15
1"
1!
1$
1%
b0 '
b0 &
b0 #
b100 (
#20
0!
0$
#25
0"
1!
1$
0%
b100 '
b100 &
b100 #
b1 (
#30
0!
0$
#35
1!
1$
b1 '
b1 &
b1 #
b110 (
#40
0!
0$
#45
1!
1$
b110 '
b110 &
b110 #
b101 (
#50
0!
0$
#55
1!
1$
b101 '
b101 &
b101 #
b10 (
#60
0!
0$
#65
1!
1$
b10 '
b10 &
b10 #
b11 (
#70
0!
0$
#75
1!
1$
b11 '
b11 &
b11 #
b111 (
#80
0!
0$
#85
1!
1$
b111 '
b111 &
b111 #
b0 (
#90
0!
0$
#95
1!
1$
b0 '
b0 &
b0 #
b100 (
#100
0!
0$
#105
1!
1$
b100 '
b100 &
b100 #
b1 (
#110
0!
0$
#115
1!
1$
b1 '
b1 &
b1 #
b110 (
#120
0!
0$
#125
1!
1$
b110 '
b110 &
b110 #
b101 (
#130
0!
0$
#135
1!
1$
b101 '
b101 &
b101 #
b10 (
#140
0!
0$
#145
1!
1$
b10 '
b10 &
b10 #
b11 (
#150
0!
0$
#155
1!
1$
b11 '
b11 &
b11 #
b111 (
#160
0!
0$
#165
1!
1$
b111 '
b111 &
b111 #
b0 (
#170
0!
0$
#175
1!
1$
b0 '
b0 &
b0 #
b100 (
#180
0!
0$
#185
1!
1$
b100 '
b100 &
b100 #
b1 (
#190
0!
0$
#195
1!
1$
b1 '
b1 &
b1 #
b110 (
