MUX_NParameter/design.sv
module mux16x1_bus (
  input [3:0] S,
  input [2:0] D0, D1, D2, D3, D4, D5, D6, D7,
              D8, D9, D10, D11, D12, D13, D14, D15,
  output reg [2:0] Y
);
  always @(*) begin
    case (S)
      4'd0: Y = D0;
      4'd1: Y = D1;
      4'd2: Y = D2;
      4'd3: Y = D3;
      4'd4: Y = D4;
      4'd5: Y = D5;
      4'd6: Y = D6;
      4'd7: Y = D7;
      4'd8: Y = D8;
      4'd9: Y = D9;
      4'd10: Y = D10;
      4'd11: Y = D11;
      4'd12: Y = D12;
      4'd13: Y = D13;
      4'd14: Y = D14;
      4'd15: Y = D15;
    endcase
  end
endmodule

MUX_NParameter/testbench.sv
module mux16x1_bus_tb();
  reg [3:0] S; // 4 bits para seleção (0 a 15)
  reg [2:0] D [0:15]; // 16 entradas de 3 bits cada
  wire [2:0] Y; // Saída do MUX

  // Instancia o DUT
  mux16x1_bus uut (
    .S(S),
    .D0(D[0]), .D1(D[1]), .D2(D[2]), .D3(D[3]),
    .D4(D[4]), .D5(D[5]), .D6(D[6]), .D7(D[7]),
    .D8(D[8]), .D9(D[9]), .D10(D[10]), .D11(D[11]),
    .D12(D[12]), .D13(D[13]), .D14(D[14]), .D15(D[15]),
    .Y(Y)
  );

  // GTKWave dump
  initial begin
    $dumpfile("dump.vcd");
    $dumpvars(0, mux16x1_bus_tb);
  end

  // Estímulos de teste
  initial begin
    D[0]  = 3'b000; D[1]  = 3'b001; D[2]  = 3'b010; D[3]  = 3'b011;
    D[4]  = 3'b100; D[5]  = 3'b101; D[6]  = 3'b110; D[7]  = 3'b111;
    D[8]  = 3'b001; D[9]  = 3'b010; D[10] = 3'b011; D[11] = 3'b100;
    D[12] = 3'b101; D[13] = 3'b110; D[14] = 3'b111; D[15] = 3'b000;

    // Testa todas as seleções
    S = 4'd0;  #10;
    S = 4'd1;  #10;
    S = 4'd2;  #10;
    S = 4'd3;  #10;
    S = 4'd4;  #10;
    S = 4'd5;  #10;
    S = 4'd6;  #10;
    S = 4'd7;  #10;
    S = 4'd8;  #10;
    S = 4'd9;  #10;
    S = 4'd10; #10;
    S = 4'd11; #10;
    S = 4'd12; #10;
    S = 4'd13; #10;
    S = 4'd14; #10;
    S = 4'd15; #10;

    $stop;
  end

  // Monitor
  initial begin
    $monitor("Tempo = %0t | S = %b | Y = %b", $time, S, Y);
  end

endmodule

MUX_NParameter/dump.vcd
$date
    May 18, 2025  15:05:30
$end
$version
    TOOL:	xmsim	23.09-s001
$end
$timescale
    1 ns
$end

$scope module mux16x1_bus_tb $end
$var reg       4 !    S [3:0] $end
$var reg       3 "    D[0] [2:0] $end
$var reg       3 #    D[1] [2:0] $end
$var reg       3 $    D[2] [2:0] $end
$var reg       3 %    D[3] [2:0] $end
$var reg       3 &    D[4] [2:0] $end
$var reg       3 '    D[5] [2:0] $end
$var reg       3 (    D[6] [2:0] $end
$var reg       3 )    D[7] [2:0] $end
$var reg       3 *    D[8] [2:0] $end
$var reg       3 +    D[9] [2:0] $end
$var reg       3 ,    D[10] [2:0] $end
$var reg       3 -    D[11] [2:0] $end
$var reg       3 .    D[12] [2:0] $end
$var reg       3 /    D[13] [2:0] $end
$var reg       3 0    D[14] [2:0] $end
$var reg       3 1    D[15] [2:0] $end
$var wire      3 2    Y [2:0] $end

$scope module uut $end
$var wire      4 3    S [3:0] $end
$var wire      3 4    D0 [2:0] $end
$var wire      3 5    D1 [2:0] $end
$var wire      3 6    D2 [2:0] $end
$var wire      3 7    D3 [2:0] $end
$var wire      3 8    D4 [2:0] $end
$var wire      3 9    D5 [2:0] $end
$var wire      3 :    D6 [2:0] $end
$var wire      3 ;    D7 [2:0] $end
$var wire      3 <    D8 [2:0] $end
$var wire      3 =    D9 [2:0] $end
$var wire      3 >    D10 [2:0] $end
$var wire      3 ?    D11 [2:0] $end
$var wire      3 @    D12 [2:0] $end
$var wire      3 A    D13 [2:0] $end
$var wire      3 B    D14 [2:0] $end
$var wire      3 C    D15 [2:0] $end
$var reg       3 D    Y [2:0] $end
$upscope $end

$upscope $end

$enddefinitions $end
$dumpvars
b0 !
b0 "
b1 #
b10 $
b11 %
b100 &
b101 '
b110 (
b111 )
b1 *
b10 +
b11 ,
b100 -
b101 .
b110 /
b111 0
b0 1
b0 2
b0 3
b0 4
b1 5
b10 6
b11 7
b100 8
b101 9
b110 :
b111 ;
b1 <
b10 =
b11 >
b100 ?
b101 @
b110 A
b111 B
b0 C
b0 D
$end
#10
b1 !
b1 3
b1 D
b1 2
#20
b10 !
b10 3
b10 D
b10 2
#30
b11 !
b11 3
b11 D
b11 2
#40
b100 !
b100 3
b100 D
b100 2
#50
b101 !
b101 3
b101 D
b101 2
#60
b110 !
b110 3
b110 D
b110 2
#70
b111 !
b111 3
b111 D
b111 2
#80
b1000 !
b1000 3
b1 D
b1 2
#90
b1001 !
b1001 3
b10 D
b10 2
#100
b1010 !
b1010 3
b11 D
b11 2
#110
b1011 !
b1011 3
b100 D
b100 2
#120
b1100 !
b1100 3
b101 D
b101 2
#130
b1101 !
b1101 3
b110 D
b110 2
#140
b1110 !
b1110 3
b111 D
b111 2
#150
b1111 !
b1111 3
b0 D
b0 2
