BCD_5311_to_BCD_8421_converter_behavior/design.sv
// Code your design here
module conversor(bcd_5311, bcd_8421);
  input [3:0] bcd_5311;
  output reg [3:0] bcd_8421;
  
  always @(*)
    case (bcd_5311)
      4'b0000: bcd_8421 = 4'b0000; //0
      4'b0001: bcd_8421 = 4'b0001; //1
      4'b0011: bcd_8421 = 4'b0010; //2
      4'b0100: bcd_8421 = 4'b0011; //3
      4'b0101: bcd_8421 = 4'b0100; //4
      4'b0111: bcd_8421 = 4'b0101; //5
      4'b1001: bcd_8421 = 4'b0110; //6
      4'b1011: bcd_8421 = 4'b0111; //7 
      4'b1100: bcd_8421 = 4'b1000; //8
      4'b1101: bcd_8421 = 4'b1001; //9
      default: bcd_8421 = 4'bxxxx;
    endcase

  endmodule

BCD_5311_to_BCD_8421_converter_behavior/testbench.sv
module conversor_tb();
  reg [3:0] bcd_5311;
  wire [3:0] bcd_8421;
  
  // Instantiate the DUT
  conversor DUT (
    .bcd_5311(bcd_5311),
    .bcd_8421(bcd_8421)
  );
  
  // Generate stimulus and monitor module ports
  initial begin
    $monitor("bcd_5311=%b, bcd_8421=%b", bcd_5311, bcd_8421);
  end
  
  // Waveform dump for simulation
  initial begin
    $dumpfile("dump.vcd");
    $dumpvars(0, conversor_tb);
  
    
    // Test cases
    bcd_5311 = 4'b0000; #10; // 0
    bcd_5311 = 4'b0001; #10; // 1
    bcd_5311 = 4'b0011; #10; // 2
    bcd_5311 = 4'b0100; #10; // 3
    bcd_5311 = 4'b0101; #10; // 4
    bcd_5311 = 4'b0111; #10; // 5
    bcd_5311 = 4'b1001; #10; // 6
    bcd_5311 = 4'b1011; #10; // 7
    bcd_5311 = 4'b1100; #10; // 8
    bcd_5311 = 4'b1101; #10; // 9
    $stop;
  end
endmodule

BCD_5311_to_BCD_8421_converter_behavior/dump.vcd
$date
    Aug 24, 2025  14:07:24
$end
$version
    TOOL:	xmsim	23.09-s001
$end
$timescale
    1 ns
$end

$scope module conversor_tb $end
$var reg       4 !    bcd_5311 [3:0] $end
$var wire      4 "    bcd_8421 [3:0] $end

$scope module DUT $end
$var wire      4 #    bcd_5311 [3:0] $end
$var reg       4 $    bcd_8421 [3:0] $end
$upscope $end

$upscope $end

$enddefinitions $end
$dumpvars
b0 !
b0 "
b0 #
b0 $
$end
#10
b1 !
b1 #
b1 $
b1 "
#20
b11 !
b11 #
b10 $
b10 "
#30
b100 !
b100 #
b11 $
b11 "
#40
b101 !
b101 #
b100 $
b100 "
#50
b111 !
b111 #
b101 $
b101 "
#60
b1001 !
b1001 #
b110 $
b110 "
#70
b1011 !
b1011 #
b111 $
b111 "
#80
b1100 !
b1100 #
b1000 $
b1000 "
#90
b1101 !
b1101 #
b1001 $
b1001 "
